{
  "6282156517421": {
    "name": "dream",
    "password": "1",
    "key": "8"
  },
  "62857757742152": {
    "name": "farel",
    "password": "farel",
    "key": "farel"
  },
  "62857757742153": {
    "name": "farel2",
    "password": "farel2",
    "key": "farel2"
  },
  "6285720677249": {
    "name": "denz",
    "password": "vip",
    "key": "2"
  },
  "6285883489759": {
    "name": "AzkingAlok",
    "password": "azking",
    "key": "azkingskibidi"
  },
  "6283857491402": {
    "name": "Zecterr",
    "password": "debi",
    "key": "debicantik"
  },
  "6287831771378": {
    "name": "sepzonly",
    "password": "VIP",
    "key": "2"
  },
  "6281918888789": {
    "name": "coconut",
    "password": "SasukeHamil",
    "key": "Brr"
  },
  "6283185180345": {
    "name": "sidx",
    "password": "sidx",
    "key": "vip"
  },
  "6287816526270": {
    "name": "zeen",
    "password": "zeen",
    "key": "zeen"
  },
  "6281324210508": {
    "name": "Fauzan",
    "password": "zannxgt",
    "key": "zannxgt"
  },
  "6282292370114": {
    "name": "HamxyzOffc",
    "password": "111",
    "key": "111"
  },
  "601137195654": {
    "name": "Zenzo viléstâ (¢)🪬",
    "password": "2010",
    "key": "2010"
  },
  "6287828270911": {
    "name": "Mandaala",
    "password": "Sigma",
    "key": "keren"
  },
  "6282214019364": {
    "name": "fadel",
    "password": "fadelsepur",
    "key": "sepuredan"
  },
  "6285137526095": {
    "name": "rymz",
    "password": "rymz123",
    "key": "64"
  },
  "6285180588369": {
    "name": "denz",
    "password": "denz",
    "key": "1"
  },
  "628999762156": {
    "name": "hulz",
    "password": "hulz",
    "key": "1"
  },
  "6282320532450": {
    "name": "riki",
    "password": "aksa",
    "key": "14"
  },
  "6283865727632": {
    "name": "VARZ",
    "password": "VARZ",
    "key": "HH"
  },
  "62882003851681": {
    "name": "hanz",
    "password": "hanz",
    "key": "1"
  },
  "66834601609": {
    "name": "denz",
    "password": "denz",
    "key": "denz"
  },
  "6285180588363": {
    "name": "1",
    "password": "1",
    "key": "1"
  },
  "6282291405622": {
    "name": "xnyo",
    "password": "xnyo",
    "key": "xnyo"
  },
  "6285175216977": {
    "name": "Randyxzall",
    "password": "Randyxzall",
    "key": "Randyxzall"
  },
  "6285135401893": {
    "name": "rymz",
    "password": "alwayzrymz",
    "key": "64"
  },
  "6285261667475": {
    "name": "xton",
    "password": "xton",
    "key": "xton"
  },
  "6282328187227": {
    "name": "sat",
    "password": "11",
    "key": "12"
  },
  "6282147966399": {
    "name": "satria",
    "password": "11",
    "key": "22"
  },
  "6281410235438": {
    "name": "rasyid",
    "password": "rasyid123",
    "key": "gak tau"
  },
  "6285921662985": {
    "name": "nirz",
    "password": "88",
    "key": "resa"
  },
  "6289663668200": {
    "name": "rey",
    "password": "rey",
    "key": "1"
  },
  "6285133734572": {
    "name": "nirz",
    "password": "1",
    "key": "1"
  },
  "6285135718125": {
    "name": "dapa",
    "password": "dapagtg",
    "key": "dapagtg"
  },
  "6285701454618": {
    "name": "junzz",
    "password": "1",
    "key": "1"
  },
  "6283133770020": {
    "name": "zenn",
    "password": "zenn",
    "key": "zenn"
  },
  "639205115743": {
    "name": "junzz",
    "password": "1",
    "key": "1"
  },
  "22892737968": {
    "name": "wil,u",
    "password": "wilzu",
    "key": "wilzu"
  },
  "628586331467": {
    "name": "wilzu",
    "password": "wilzu",
    "key": "wilzu"
  },
  "6285753953900": {
    "name": "kepa",
    "password": "kepanya123",
    "key": "scbug"
  }
}
